notebooktester/__init__.py
notebooktester/cli.py
notebooktester/main.py
notebooktester-0.1.2.dist-info/METADATA
notebooktester-0.1.2.dist-info/WHEEL
notebooktester-0.1.2.dist-info/entry_points.txt
notebooktester-0.1.2.dist-info/RECORD
