Metadata-Version: 2.4
Name: notebooktester
Version: 0.1.2
Summary: Add your description here
Author-email: raoul grouls <Raoul.Grouls@han.nl>
Requires-Python: >=3.11
Requires-Dist: click>=8.1.8
Requires-Dist: jupyter>=1.1.1
Requires-Dist: loguru>=0.7.3
Requires-Dist: tqdm>=4.67.1
